sbencryptor/__init__.py
sbencryptor/decrypt.py
sbencryptor/encrypt.py
sbencryptor-0.0.1.dist-info/LICENCE
sbencryptor-0.0.1.dist-info/METADATA
sbencryptor-0.0.1.dist-info/WHEEL
sbencryptor-0.0.1.dist-info/top_level.txt
sbencryptor-0.0.1.dist-info/RECORD
