Metadata-Version: 2.1
Name: sbencryptor
Version: 0.0.1
Summary: Sbencryptor Test Package for image encryption Demo
Home-page: UNKNOWN
Author: Saber Bejestani
Author-email: saberbejestani@gmail.com
License: UNKNOWN
Platform: UNKNOWN
Classifier: Programming Language :: Python :: 3
Classifier: License :: OSI Approved :: MIT License
Classifier: Operating System :: OS Independent
Requires-Python: >=3.6
License-File: LICENCE
